Workbook

Sheet Readme
B2: Model by: | C2: Jay Prakash
B3: Website: | C3: https://jay-finance.github.io/portfolio/

Sheet Calc
B2: Index Valuation & Implied Risk Premium Calculator - S&P 500
B4: Inputs | F4: Cash Flow Choice | Z4: Jan | AA4: =AA5+1 -> 12 | AB4: Last Year | AC4: Last 12 Months
Z5: Feb | AA5: =AA6+1 -> 11 | AB5: Last 4 Quarters | AC5: 5 Years
B6: Month | D6: Oct | F6: Choose Cash Yield Average | I6: A | Z6: Mar | AA6: =AA7+1 -> 10 | AC6: 10 Years
B7: Base Year | D7: Last 4 Quarters | F7: Dividends and Buybacks Trailing 12 months | I7: =Yield!I39 -> 198.88565 | J7: A | K7: Dividends + Buybacks in Trailing 12 Months | Z7: Apr | AA7: =AA8+1 -> 9
B8: Enter Index Level | D8: 7773.95 | F8: Dividends and Buybacks (Average yield- last decade) | I8: =Yield!K28*Calc!D8 -> 332.47587 | J8: B | K8: Multiplies average cash yield over last 10 years by index level at the start of most recent quarter | Z8: May | AA8: =AA9+1 -> 8
B9: Base Cash Yield | D9: =IF(I6=J7,I7/D8,IF(I6=J8,I8/D8,I9/D8)) -> 0.025583603 | F9: Dividends and Buybacks (Average payout- last decade) | I9: =Yield!J28*Yield!D39 -> 206.35517 | J9: C | K9: Multiplies Earnings in last 12 months by average payout ratio over last 10 years | Z9: Jun | AA9: =AA10+1 -> 7
Z10: Jul | AA10: =AA11+1 -> 6
B11: Discount Rate Inputs | F11: Growth Rate Choice | Z11: Aug | AA11: =AA12+1 -> 5
Z12: Sep | AA12: =AA13+1 -> 4
B13: Enter Government Yield | D13: 0.0528 | F13: Choose Cash Yield Average | I13: A | Z13: Oct | AA13: =AA14+1 -> 3
B14: CDS Spread - United States | D14: 0.0057 | F14: Top-Down Consensus Estimate | I14: =Growth!C9 -> 0.11399371 | J14: A | Z14: Nov | AA14: =AA15+1 -> 2
B15: CDS Spread - Switzerland | D15: 0.0014 | F15: Historical Earnings Growth (last decade) | I15: =_xlfn.RRI(10,Yield!D17,Yield!D39) -> 0.088240181 | J15: B | Z15: Dec | AA15: 1
B16: Risk-Free Rate - United States | D16: =D13-(D14-D15) -> 0.0485 | F16: Intrinsic Growth (Average ROE - last decade) | I16: =(1-((D9*D8)/D24))*Yield!M28 -> 0.027061211 | J16: C
B18: Choose Risk Premium Average | D18: 10 Years | F18: Use Risk-Free Rate as Long Term Growth Rate? | I18: Yes
B19: Selected Risk Premium | D19: =VLOOKUP(D18,RiskPrem!$K$3:$L$5,2,FALSE) -> 0.035925092 | F19: If "No" Enter The Preferred Long Term Growth Rate | I19: 0.03
B21: Intrinsic Value of the Index
D23: Base Year | E23: 1 | F23: =E23+1 -> 2 | G23: =F23+1 -> 3 | H23: =G23+1 -> 4 | I23: =H23+1 -> 5 | J23: Terminal Year
B24: Expected Earnings | D24: =IF(D7="Last Year",Yield!D26,Yield!D39) -> 234.06 | E24: =IF($I$13=$J$14,D24*(1+$I$14),IF($I$13=$J$15,D24*(1+$I$15),D24*(1+$I$16))) -> 260.74137 | F24: =IF($I$13=$J$14,E24*(1+$I$14),IF($I$13=$J$15,E24*(1+$I$15),E24*(1+$I$16))) -> 290.46424 | G24: =IF($I$13=$J$14,F24*(1+$I$14),IF($I$13=$J$15,F24*(1+$I$15),F24*(1+$I$16))) -> 323.57534 | H24: =IF($I$13=$J$14,G24*(1+$I$14),IF($I$13=$J$15,G24*(1+$I$15),G24*(1+$I$16))) -> 360.46089 | I24: =IF($I$13=$J$14,H24*(1+$I$14),IF($I$13=$J$15,H24*(1+$I$15),H24*(1+$I$16))) -> 401.55116 | J24: =IF(I18="Yes",I24*(1+D16),I24*(1+I19)) -> 421.0264
B25: =IF($I$6="A",$F$7,IF($I$6="B",$F$8,$F$9)) -> Dividends and Buybacks Trailing 12 months | D25: =D26/D24 -> 0.84972079 | E25: =D25 -> 0.84972079 | F25: =E25 -> 0.84972079 | G25: =F25 -> 0.84972079 | H25: =G25 -> 0.84972079 | I25: =H25 -> 0.84972079 | J25: =I25 -> 0.84972079
B26: Expected Cash to Equity | D26: =IF(I6="A",I7,IF(I6="B",I8,I9)) -> 198.88565 | E26: =E24*E25 -> 221.55736 | F26: =F24*F25 -> 246.81351 | G26: =G24*G25 -> 274.94869 | H26: =H24*H25 -> 306.29111 | I26: =I24*I25 -> 341.20637 | J26: =J24*J25 -> 357.75488
B27: Expected Terminal Value | I27: =IF(I18="Yes",J26/(D16+D19-D16),J26/(D16+D19-I19)) -> 9958.3566
B29: Time to cashflow | E29: =VLOOKUP(D6,$Z$4:$AA$15,2,FALSE)/12 -> 0.25 | F29: =E29+1 -> 1.25 | G29: =F29+1 -> 2.25 | H29: =G29+1 -> 3.25 | I29: =H29+1 -> 4.25
B30: Present Value | E30: =E26*E29/(1+$D$16+$D$19)^E29 -> 54.278308 | F30: =F26/(1+$D$16+$D$19)^F29 -> 223.03318 | G30: =G26/(1+$D$16+$D$19)^G29 -> 229.11454 | H30: =H26/(1+$D$16+$D$19)^H29 -> 235.36172 | I30: =(I26+I27)/(1+$D$16+$D$19)^I29 -> 7298.2826
B32: Intrinsic Value of Index | J32: =SUM(E30:I30) -> 8040.0704
B34: Implied Equity Risk Premium Calculator
B36: Risk-Free Rate | D36: =D16 -> 0.0485
B37: Implied Cost of Capital | D37: =D36+D38 -> 0.085639909
B38: Implied Equity Risk Premium | D38: 0.037139909
D40: Base Year | E40: 1 | F40: =E40+1 -> 2 | G40: =F40+1 -> 3 | H40: =G40+1 -> 4 | I40: =H40+1 -> 5 | J40: Terminal Year
B41: Expected Earnings | D41: =D24 -> 234.06 | E41: =E24 -> 260.74137 | F41: =F24 -> 290.46424 | G41: =G24 -> 323.57534 | H41: =H24 -> 360.46089 | I41: =I24 -> 401.55116 | J41: =J24 -> 421.0264
B42: =IF($I$6="A",$F$7,IF($I$6="B",$F$8,$F$9)) -> Dividends and Buybacks Trailing 12 months | D42: =D43/D41 -> 0.84972079 | E42: =D42 -> 0.84972079 | F42: =E42 -> 0.84972079 | G42: =F42 -> 0.84972079 | H42: =G42 -> 0.84972079 | I42: =H42 -> 0.84972079 | J42: =I42 -> 0.84972079
B43: Expected Cash to Equity | D43: =D26 -> 198.88565 | E43: =E41*E42 -> 221.55736 | F43: =F41*F42 -> 246.81351 | G43: =G41*G42 -> 274.94869 | H43: =H41*H42 -> 306.29111 | I43: =I41*I42 -> 341.20637 | J43: =J41*J42 -> 357.75488
B44: Expected Terminal Value | I44: =IF(I18="Yes",J43/(D36+D38-D36),J43/(D36+D38-I19)) -> 9632.6269
B46: Time to cashflow | E46: =E29 -> 0.25 | F46: =F29 -> 1.25 | G46: =G29 -> 2.25 | H46: =H29 -> 3.25 | I46: =I29 -> 4.25
B47: Present Value | E47: =E43*E46/(1+$D$36+$D$38)^E46 -> 54.263118 | F47: =F43/(1+$D$36+$D$38)^F46 -> 222.72126 | G47: =G43/(1+$D$36+$D$38)^G46 -> 228.5381 | H47: =H43/(1+$D$36+$D$38)^H46 -> 234.50686 | I47: =(I43+I44)/(1+$D$36+$D$38)^I46 -> 7033.9205
B49: Intrinsic Value of Index | J49: =SUM(E47:I47) -> 7773.9498

Sheet Yield
B2: Year | C2: Market value of index | D2: Earnings | E2: Dividends | F2: Buybacks | G2: Dividends yield | H2: Buyback yield | I2: Cash to equity | J2: Payout | K2: Gross Cash Yield | L2: Book Value of Equity | M2: Return on Equity
B3: 2001 | C3: 1148.09 | D3: 38.85 | E3: 15.74 | F3: 14.339958 | G3: =E3/C3 -> 0.013709727 | H3: =F3/C3 -> 0.012490273 | I3: =E3+F3 -> 30.079958 | J3: =(E3+F3)/D3 -> 0.77425889 | K3: =H3+G3 -> 0.0262 | L3: 325.8 | M3: =D3/L3 -> 0.11924494
B4: 2002 | C4: 879.82 | D4: 46.04 | E4: 15.96 | F4: 13.865898 | G4: =E4/C4 -> 0.018140074 | H4: =F4/C4 -> 0.015759926 | I4: =E4+F4 -> 29.825898 | J4: =(E4+F4)/D4 -> 0.64782576 | K4: =H4+G4 -> 0.0339 | L4: 338.37 | M4: =D4/L4 -> 0.13606407
B5: 2003 | C5: 1111.91 | D5: 54.69 | E5: 17.88 | F5: 13.698244 | G5: =E5/C5 -> 0.016080438 | H5: =F5/C5 -> 0.012319562 | I5: =E5+F5 -> 31.578244 | J5: =(E5+F5)/D5 -> 0.57740435 | K5: =H5+G5 -> 0.0284 | L5: 325.72 | M5: =D5/L5 -> 0.16790495
B6: 2004 | C6: 1211.92 | D6: 67.68 | E6: 19.01 | F6: 21.58932 | G6: =E6/C6 -> 0.015685854 | H6: =F6/C6 -> 0.017814146 | I6: =E6+F6 -> 40.59932 | J6: =(E6+F6)/D6 -> 0.59987175 | K6: =H6+G6 -> 0.0335 | L6: 367.17 | M6: =D6/L6 -> 0.18432879
B7: 2005 | C7: 1248.29 | D7: 76.45 | E7: 22.344391 | F7: 38.821819 | G7: =E7/C7 -> 0.0179 | H7: =F7/C7 -> 0.0311 | I7: =E7+F7 -> 61.16621 | J7: =(E7+F7)/D7 -> 0.80008123 | K7: =H7+G7 -> 0.049 | L7: 414.75 | M7: =D7/L7 -> 0.18432791
B8: 2006 | C8: 1418.3 | D8: 87.72 | E8: 25.04226 | F8: 48.11568 | G8: =E8/C8 -> 0.017656532 | H8: =F8/C8 -> 0.033924896 | I8: =E8+F8 -> 73.15794 | J8: =(E8+F8)/D8 -> 0.83399384 | K8: =H8+G8 -> 0.051581428 | L8: 453.06 | M8: =D8/L8 -> 0.19361674
B9: 2007 | C9: 1468.36 | D9: 82.54 | E9: 28.138242 | F9: 67.224141 | G9: =E9/C9 -> 0.01916304 | H9: =F9/C9 -> 0.045781784 | I9: =E9+F9 -> 95.362382 | J9: =(E9+F9)/D9 -> 1.1553475 | K9: =H9+G9 -> 0.064944824 | L9: 504.39 | M9: =D9/L9 -> 0.16364321
B10: 2008 | C10: 903.25 | D10: 49.51 | E10: 28.446853 | F10: 39.070279 | G10: =E10/C10 -> 0.031493887 | H10: =F10/C10 -> 0.043255222 | I10: =E10+F10 -> 67.517132 | J10: =(E10+F10)/D10 -> 1.363707 | K10: =H10+G10 -> 0.074749109 | L10: 529.59 | M10: =D10/L10 -> 0.093487415
B11: 2009 | C11: 1115 | D11: 56.86 | E11: 21.96869 | F11: 15.459282 | G11: =E11/C11 -> 0.019702861 | H11: =F11/C11 -> 0.013864827 | I11: =E11+F11 -> 37.427971 | J11: =(E11+F11)/D11 -> 0.65824783 | K11: =H11+G11 -> 0.033567687 | L11: 451.37 | M11: =D11/L11 -> 0.12597204
B12: 2010 | C12: 1257.64 | D12: 83.77 | E12: 22.647423 | F12: 32.879089 | G12: =E12/C12 -> 0.018007874 | H12: =F12/C12 -> 0.026143482 | I12: =E12+F12 -> 55.526511 | J12: =(E12+F12)/D12 -> 0.66284483 | K12: =H12+G12 -> 0.044151356 | L12: 513.58 | M12: =D12/L12 -> 0.16310993
B13: 2011 | C13: 1257.6 | D13: 96.44 | E13: 26.532764 | F13: 44.745596 | G13: =E13/C13 -> 0.021097936 | H13: =F13/C13 -> 0.035580149 | I13: =E13+F13 -> 71.27836 | J13: =(E13+F13)/D13 -> 0.7390954 | K13: =H13+G13 -> 0.056678085 | L13: 579.14 | M13: =D13/L13 -> 0.16652278
B14: 2012 | C14: 1426.19 | D14: 96.82 | E14: 31.25 | F14: 44.649306 | G14: =E14/C14 -> 0.021911527 | H14: =F14/C14 -> 0.031306702 | I14: =E14+F14 -> 75.899306 | J14: =(E14+F14)/D14 -> 0.78392177 | K14: =H14+G14 -> 0.053218229 | L14: 613.14 | M14: =D14/L14 -> 0.15790847
... B26: 2024 | C26: 5580.94 | D26: 232.33 | E26: 74.35 | F26: 111.3 | G26: =E26/C26 -> 0.013322129 | H26: =F26/C26 -> 0.019942877 | I26: =E26+F26 -> 185.65 | J26: =(E26+F26)/D26 -> 0.7990789 | K26: =H26+G26 -> 0.033265006 | L26: 1106.2 | M26: =D26/L26 -> 0.21002531
B28: Average 10 years | G28: =AVERAGE(G17:G26) -> 0.017311489 | H28: =AVERAGE(H17:H26) -> 0.025456457 | J28: =AVERAGE(J18:J26) -> 0.88163363 | K28: =G28+H28 -> 0.042767946 | M28: =AVERAGE(M17:M26) -> 0.18007289
B29: Average 5 years | G29: =AVERAGE(G22:G26) -> 0.014671845 | H29: =AVERAGE(H22:H26) -> 0.021335775 | J29: =AVERAGE(J23:J26) -> 0.81787403 | K29: =G29+H29 -> 0.03600762 | M29: =AVERAGE(M22:M26) -> 0.19752885
B32: Last 12 Months | D32: Earnings | E32: Dividends | F32: Buybacks | G32: Dividends Yield | H32: Buybacks Yield | I32: Cash to Equity | J32: Payout Ratio | K32: Gross Cash Yield | L32: Book Value | M32: Return on Equity
B33: Q4 2024 | D33: 57.69 | E33: 19.81 | F33: 28.75 | L33: 1178.5678
B34: Q1 2025 | D34: 53.89 | E34: 19.372895 | F34: 34.65 | L34: 1197.1102
B35: Q2 2025 | D35: 58.96 | E35: 19.484935 | F35: 27.67 | L35: 1238.9269
B36: Q3 2025 | D36: 63.52 | E36: 19.807819 | F36: 29.34 | L36: 1270.322
B37: Q4 2025 | D37: S&P has not updated the earnings , buybacks and Book Value for Q4
B39: Last 12 Months | C39: 6845.5 | D39: =SUM(D33:D36) -> 234.06 | E39: =SUM(E33:E36) -> 78.475649 | F39: =SUM(F33:F36) -> 120.41 | G39: =E39/C39 -> 0.01146383 | H39: =F39/C39 -> 0.017589657 | I39: =E39+F39 -> 198.88565 | J39: =(E39+F39)/D39 -> 0.84972079 | K39: =H39+G39 -> 0.029053487 | L39: =L36 -> 1270.322 | M39: =D39/L39 -> 0.1842525

Sheet Growth
B2: Consensus Estimates
B3: 2026 | C3: =D30 -> 0.16421569
B4: =B3+1 -> 2027 | C4: =E30 -> 0.13416501
B5: =B4+1 -> 2028 | C5: =C4-($C$4-$C$8)/($B$8-$B$4) -> 0.11274876
B6: =B5+1 -> 2029 | C6: =C5-($C$4-$C$8)/($B$8-$B$4) -> 0.091332507
B7: =B6+1 -> 2030 | C7: =C6-($C$4-$C$8)/($B$8-$B$4) -> 0.069916253
B8: =B7+1 -> 2031 | C8: =IF(Calc!I18="Yes",Calc!D16,Calc!I19) -> 0.0485
B9: 5Y CAGR | C9: =((1+C3)*(1+C4)*(1+C5)*(1+C6)*(1+C7))^(1/5)-1 -> 0.11399371
B11: Source | C11: FY25A EPS | D11: FY26E EPS | E11: FY27E EPS
B12: Goldman Sachs | C12: 272 | D12: 309 | E12: 342
D13: =D12/C12-1 -> 0.13602941 | E13: =E12/D12-1 -> 0.10679612
B15: JP Morgan | C15: 272 | D15: 330 | E15: 385
D16: =D15/C15-1 -> 0.21323529 | E16: =E15/D15-1 -> 0.16666667
B18: BofA | C18: 272 | D18: 310
D19: =D18/C18-1 -> 0.13970588
B21: Deutshe Bank | C21: 272 | D21: 320
D22: =D21/C21-1 -> 0.17647059
B24: Wells Fargo | C24: 272 | D24: 310 | E24: 350
D25: =D24/C24-1 -> 0.13970588 | E25: =E24/D24-1 -> 0.12903226
B27: Barclays | C27: 272 | D27: 321
D28: =D27/C27-1 -> 0.18014706
B30: Consensus avg | D30: =AVERAGE(D28,D25,D22,D19,D16,D13) -> 0.16421569 | E30: =AVERAGE(E28,E25,E22,E19,E16,E13) -> 0.13416501

Sheet RiskPrem
B2: Year | C2: ICOC | D2: Risk-Free Rate | E2: IERP | G2: Year | H2: Implied Risk Premium | J2: Average Risk Premiums
B3: 37392 | C3: 0.08159 | D3: =C3-E3 -> 0.052 | E3: 0.02959 | G3: 2002 | H3: =AVERAGEIFS($E$3:$E$291,$B$3:$B$291,">="&DATE(G3,1,1),$B$3:$B$291,"<="&DATE(G3,12,31)) -> 0.03801875 | J3: Average | K3: Last 12 Months | L3: =AVERAGE(H27) -> 0.026340868
B4: 37427 | C4: 0.08209 | D4: =C4-E4 -> 0.0485 | E4: 0.03359 | G4: =G3+1 -> 2003 | H4: =AVERAGEIFS($E$3:$E$291,$B$3:$B$291,">="&DATE(G4,1,1),$B$3:$B$291,"<="&DATE(G4,12,31)) -> 0.0368975 | J4: Average | K4: 5 Years | L4: =AVERAGE(H22:H26) -> 0.029556352
B5: 37455 | C5: 0.08526 | D5: =C5-E5 -> 0.0466 | E5: 0.03866 | G5: =G4+1 -> 2004 | H5: =AVERAGEIFS($E$3:$E$291,$B$3:$B$291,">="&DATE(G5,1,1),$B$3:$B$291,"<="&DATE(G5,12,31)) -> 0.0340875 | J5: Average | K5: 10 Years | L5: =AVERAGE(H17:H26) -> 0.035925092
B6: 37483 | C6: 0.08189 | D6: =C6-E6 -> 0.0417 | E6: 0.04019 | G6: =G5+1 -> 2005 | H6: =AVERAGEIFS($E$3:$E$291,$B$3:$B$291,">="&DATE(G6,1,1),$B$3:$B$291,"<="&DATE(G6,12,31)) -> 0.036973333
B7: 37518 | C7: 0.08179 | D7: =C7-E7 -> 0.0379 | E7: 0.04389 | G7: =G6+1 -> 2006 | H7: =AVERAGEIFS($E$3:$E$291,$B$3:$B$291,">="&DATE(G7,1,1),$B$3:$B$291,"<="&DATE(G7,12,31)) -> 0.0361725 | J7: Souce: Market-Risk-premia
B8: 37546 | C8: 0.0818 | D8: =C8-E8 -> 0.0416 | E8: 0.0402 | G8: =G7+1 -> 2007 | H8: =AVERAGEIFS($E$3:$E$291,$B$3:$B$291,">="&DATE(G8,1,1),$B$3:$B$291,"<="&DATE(G8,12,31)) -> 0.0366175
B9: 37574 | C9: 0.07961 | D9: =C9-E9 -> 0.0403 | E9: 0.03931 | G9: =G8+1 -> 2008 | H9: =AVERAGEIFS($E$3:$E$291,$B$3:$B$291,">="&DATE(G9,1,1),$B$3:$B$291,"<="&DATE(G9,12,31)) -> 0.0567675
B10: 37609 | C10: 0.07832 | D10: =C10-E10 -> 0.0396 | E10: 0.03872 | G10: =G9+1 -> 2009 | H10: =AVERAGEIFS($E$3:$E$291,$B$3:$B$291,">="&DATE(G10,1,1),$B$3:$B$291,"<="&DATE(G10,12,31)) -> 0.057725833
B11: 37637 | C11: 0.07682 | D11: =C11-E11 -> 0.041 | E11: 0.03582 | G11: =G10+1 -> 2010 | H11: =AVERAGEIFS($E$3:$E$291,$B$3:$B$291,">="&DATE(G11,1,1),$B$3:$B$291,"<="&DATE(G11,12,31)) -> 0.053345833
B12: 37672 | C12: 0.08534 | D12: =C12-E12 -> 0.0385 | E12: 0.04684 | G12: =G11+1 -> 2011 | H12: =AVERAGEIFS($E$3:$E$291,$B$3:$B$291,">="&DATE(G12,1,1),$B$3:$B$291,"<="&DATE(G12,12,31)) -> 0.057633333
B13: 37700 | C13: 0.08242 | D13: =C13-E13 -> 0.0401 | E13: 0.04232 | G13: =G12+1 -> 2012 | H13: =AVERAGEIFS($E$3:$E$291,$B$3:$B$291,">="&DATE(G13,1,1),$B$3:$B$291,"<="&DATE(G13,12,31)) -> 0.062174167
B14: 37728 | C14: 0.08086 | D14: =C14-E14 -> 0.0398 | E14: 0.04106 | G14: =G13+1 -> 2013 | H14: =AVERAGEIFS($E$3:$E$291,$B$3:$B$291,">="&DATE(G14,1,1),$B$3:$B$291,"<="&DATE(G14,12,31)) -> 0.049065833
B15: 37756 | C15: 0.07598 | D15: =C15-E15 -> 0.0353 | E15: 0.04068 | G15: =G14+1 -> 2014 | H15: =AVERAGEIFS($E$3:$E$291,$B$3:$B$291,">="&DATE(G15,1,1),$B$3:$B$291,"<="&DATE(G15,12,31)) -> 0.043009167
B16: 37791 | C16: 0.0708 | D16: =C16-E16 -> 0.0335 | E16: 0.0373 | G16: =G15+1 -> 2015 | H16: =AVERAGEIFS($E$3:$E$291,$B$3:$B$291,">="&DATE(G16,1,1),$B$3:$B$291,"<="&DATE(G16,12,31)) -> 0.043008333
B17: 37819 | C17: 0.07628 | D17: =C17-E17 -> 0.0398 | E17: 0.03648 | G17: =G16+1 -> 2016 | H17: =AVERAGEIFS($E$3:$E$291,$B$3:$B$291,">="&DATE(G17,1,1),$B$3:$B$291,"<="&DATE(G17,12,31)) -> 0.045871667
B18: 37847 | C18: 0.079 | D18: =C18-E18 -> 0.0455 | E18: 0.0335 | G18: =G17+1 -> 2017 | H18: =AVERAGEIFS($E$3:$E$291,$B$3:$B$291,">="&DATE(G18,1,1),$B$3:$B$291,"<="&DATE(G18,12,31)) -> 0.037279167
B19: 37882 | C19: 0.07483 | D19: =C19-E19 -> 0.0419 | E19: 0.03293 | G19: =G18+1 -> 2018 | H19: =AVERAGEIFS($E$3:$E$291,$B$3:$B$291,">="&DATE(G19,1,1),$B$3:$B$291,"<="&DATE(G19,12,31)) -> 0.038923333
... B26: 38092 | C26: 0.07698 | D26: =C26-E26 -> 0.0442 | E26: 0.03278 | G26: =G25+1 -> 2025 | H26: =AVERAGEIFS($E$3:$E$291,$B$3:$B$291,">="&DATE(G26,1,1),$B$3:$B$291,"<="&DATE(G26,12,31)) -> 0.024235765
B27: 38127 | C27: 0.08176 | D27: =C27-E27 -> 0.0472 | E27: 0.03456 | G27: Last 12 Months | H27: =AVERAGE(E279:E290) -> 0.026340868
B28: 38155 | C28: 0.07952 | D28: =C28-E28 -> 0.0471 | E28: 0.03242
B29: 38183 | C29: 0.07943 | D29: =C29-E29 -> 0.045 | E29: 0.03443
B30: 38218 | C30: 0.07902 | D30: =C30-E30 -> 0.0422 | E30: 0.03682
B31: 38246 | C31: 0.07728 | D31: =C31-E31 -> 0.0408 | E31: 0.03648
B32: 38274 | C32: 0.07723 | D32: =C32-E32 -> 0.0403 | E32: 0.03693
B33: 38309 | C33: 0.07526 | D33: =C33-E33 -> 0.0412 | E33: 0.03406
B34: 38337 | C34: 0.07465 | D34: =C34-E34 -> 0.0419 | E34: 0.03275
B35: 38372 | C35: 0.07632 | D35: =C35-E35 -> 0.0417 | E35: 0.03462
B36: 38400 | C36: 0.07774 | D36: =C36-E36 -> 0.0419 | E36: 0.03584
B37: 38428 | C37: 0.08124 | D37: =C37-E37 -> 0.0447 | E37: 0.03654
B38: 38456 | C38: 0.08163 | D38: =C38-E38 -> 0.0437 | E38: 0.03793
B39: 38491 | C39: 0.07948 | D39: =C39-E39 -> 0.0411 | E39: 0.03838
... B288: 46081 | C288: 0.067629707 | D288: =C288-E288 -> 0.0397 | E288: 0.027929707
B289: 46082 | E289: 0.0374
B290: 46113 | E290: 0.0409
B291: 46143 | E291: 0.0373
